marslib/__init__.py
marslib/configurator.py
marslib/connection.py
marslib/executor.py
marslib/parser.py
marslib/query.py
marslib-1.1.1.dist-info/LICENSE
marslib-1.1.1.dist-info/METADATA
marslib-1.1.1.dist-info/WHEEL
marslib-1.1.1.dist-info/top_level.txt
marslib-1.1.1.dist-info/RECORD
